servpy/__init__.py
servpy/constants.py
servpy/discovery_server.py
servpy/input_processor.py
servpy/main.py
servpy/models.py
servpy/request_processor.py
servpy/service_configuration.py
servpy/utils.py
servpy/watchdog.py
ServerPy-0.0.2.dist-info/LICENSE
ServerPy-0.0.2.dist-info/METADATA
ServerPy-0.0.2.dist-info/WHEEL
ServerPy-0.0.2.dist-info/entry_points.txt
ServerPy-0.0.2.dist-info/top_level.txt
ServerPy-0.0.2.dist-info/RECORD
