Metadata-Version: 2.1
Name: ServerPy
Version: 0.0.2
Summary: Resource Discovery and Request forwarding library
Home-page: UNKNOWN
Author: Divyansh Chopra
License: UNKNOWN
Platform: UNKNOWN
Classifier: Programming Language :: Python :: 3
Classifier: License :: OSI Approved :: MIT License
Classifier: Operating System :: OS Independent
Requires-Python: >=3.6
Requires-Dist: PyYAML (==6.0)
Requires-Dist: web.py (==0.62)
Requires-Dist: requests (==2.28.0)
